functions.py
functions_for_TAQR.py
helper_functions.py
nabqr.py
visualization.py
nabqr/__init__.py
nabqr/functions.py
nabqr/functions_for_TAQR.py
nabqr/helper_functions.py
nabqr/info.py
nabqr/nabqr.py
nabqr/nabqr2.py
nabqr/visualization.py
nabqr-0.0.54.dist-info/AUTHORS.rst
nabqr-0.0.54.dist-info/LICENSE
nabqr-0.0.54.dist-info/METADATA
nabqr-0.0.54.dist-info/WHEEL
nabqr-0.0.54.dist-info/top_level.txt
nabqr-0.0.54.dist-info/RECORD
