Metadata-Version: 2.1
Name: nabqr
Version: 0.0.54
Summary: NABQR is a method for sequential error-corrections tailored for wind power forecast in Denmark
Home-page: https://github.com/bast0320/nabqr
Author: Bastian S. Jørgensen
Author-email: bassc@dtu.dk
License: MIT
Keywords: nabqr,energy,quantile,forecasting
Classifier: Development Status :: 4 - Beta
Classifier: Environment :: Console
Classifier: Intended Audience :: Developers
Classifier: Natural Language :: English
Classifier: License :: OSI Approved :: BSD License
Classifier: Programming Language :: Python
Classifier: Programming Language :: Python :: 3
Classifier: Programming Language :: Python :: 3.10
Classifier: Programming Language :: Python :: 3.11
Classifier: Programming Language :: Python :: 3.12
Classifier: Topic :: Software Development
Requires-Python: >=3.10
License-File: LICENSE
License-File: AUTHORS.rst
Requires-Dist: icecream >=2.1.3
Requires-Dist: matplotlib >=3.8.4
Requires-Dist: numpy >=1.26.0
Requires-Dist: pandas >=2.2.3
Requires-Dist: properscoring >=0.1
Requires-Dist: rich >=13.9.4
Requires-Dist: SciencePlots ==2.1.1
Requires-Dist: scikit-learn >=1.4.2
Requires-Dist: scipy >=1.14.1
Requires-Dist: tensorflow >=2.16.1
Requires-Dist: tensorflow-probability >=0.24.0
Requires-Dist: torch >=2.4.1
Requires-Dist: typer >=0.13.1
Requires-Dist: sphinx-rtd-theme >=3.0.2
Requires-Dist: myst-parser >=4.0.0
Requires-Dist: tf-keras >=2.16.0
Requires-Dist: autodocsumm >=0.2.14
Requires-Dist: sphinx-mdinclude >=0.6.2
Provides-Extra: docs
Requires-Dist: sphinx >=4.0.0 ; extra == 'docs'
Requires-Dist: sphinx-rtd-theme ; extra == 'docs'
Requires-Dist: sphinx-autodoc-typehints ; extra == 'docs'
Requires-Dist: autodocsumm ; extra == 'docs'
Requires-Dist: sphinx-mdinclude ; extra == 'docs'
